Metadata-Version: 2.1
Name: redis-persistence
Version: 0.0.4
Summary: A python module to make your Telegram bot persistent using Redis
Home-page: https://github.com/Mortafix/RedisPersistence
Author: Moris Doratiotto
Author-email: moris.doratiotto@gmail.com
License: UNKNOWN
Keywords: persistence,persistent,redis,telegram,bot
Platform: UNKNOWN
Classifier: Programming Language :: Python :: 3.8
Classifier: License :: OSI Approved :: MIT License
Classifier: Operating System :: OS Independent
Classifier: Development Status :: 3 - Alpha
Classifier: Intended Audience :: Developers
Requires-Python: >=3.8
